src/module/control_unit.v
module control_unit (
    input wire clk, reset,
    input wire [3:0] opcode,      // from IR[7:4]
    output reg PC_out, PC_in, PC_inc, MAR_in, MEM_rd, MEM_wr, IR_in, IR_out,
    output reg A_in, B_in, ALU_out,
    output reg [2:0] ALU_op,     
    output reg [3:0] state        
);

    // Opcode format 
    localparam OP_LDA   = 4'b0000, // load A
                OP_ADDA  = 4'b0001, // add A with value in memory
                OP_SUBA  = 4'b0010, // sub A with value in memory
                OP_ADDAI = 4'b0011, // add A with immediate value 
                OP_SUBAI = 4'b0100, // sub A with immediate value
                OP_STRA  = 4'b0101, // store A to address in IR[3:0]  
                OP_MOVAB = 4'b0110, // mov A to B
                
                OP_LDB   = 4'b1000, // load B
                OP_ADDB  = 4'b1001, // add B with value in memory
                OP_SUBB  = 4'b1010, // sub B with value in memory
                OP_ADDBI = 4'b1011, // add B with immediate value 
                OP_SUBBI = 4'b1100, // sub B with immediate value
                OP_STRB  = 4'b1101, // store B to address in IR[3:0] 
                OP_MOVBA = 4'b1110; // mov B to A 
                
    // State definitions
    localparam T0       = 0,
                T1       = 1, // FETCH IR 
                T2       = 2, // DECODE IR
                LDA_st1  = 4, // Load A part 1
                LDA_st2  = 5, // Load A part 2 
                ADDA_st1 = 6, // Add A part 1
                ADDA_st2 = 7, // Add A part 2
                ADDA_st3 = 8, // Add A part 3 (ALU result to A)
                SUBA_st1 = 9, // SUB A part 1
                SUBA_st2 = 10,// SUB A part 2
                SUBA_st3 = 11,// SUB A part 3
                ADDAI_st1= 12,// ADD A immediate part 1
                ADDAI_st2= 13,// ADD A immediate part 2
                SUBAI_st1= 14,// SUB A immediate part 1
                SUBAI_st2= 15,// SUB A immediate part 2
                STRA_st  = 16,// STORE A with address in IR
                MOVAB_st = 17,// MOVE A to B 
                LDB_st1  = 18,// Load B part 1
                LDB_st2  = 19,// Load B part 2 
                ADDB_st1 = 20,// Add B part 1
                ADDB_st2 = 21,// Add B part 2
                ADDB_st3 = 22,// Add B part 3
                SUBB_st1 = 23,// SUB B part 1
                SUBB_st2 = 24,// SUB B part 2
                SUBB_st3 = 25,// SUB B part 3
                ADDBI_st1= 26,// ADD B immediate part 1
                ADDBI_st2= 27,// ADD B immediate part 2
                SUBBI_st1= 28,// SUB B immediate part 1
                SUBBI_st2= 29,// SUB B immediate part 2
                STRB_st  = 30,// STORE B with address in IR
                MOVBA_st = 31;// MOVE B to A 

    // ALU opcode 
    localparam A_add_B  = 3'b000,
                A_sub_B = 3'b001,
                B_sub_A = 3'b010,
                Pass_A  = 3'b011,
                Pass_B  = 3'b100,
                A_mul_B = 3'b101,
                A_div_B = 3'b110,
                B_div_A = 3'b111;
    
    /* ------- State machine ------ */
    always @(posedge clk or posedge reset) begin
    
        /* ------- Default signal values ----- */
        {PC_out, PC_inc, MAR_in, MEM_rd, IR_in, IR_out, A_in, B_in, ALU_out} = 0;
        {PC_in, MEM_wr} = 0;
        ALU_op = 0;

        /* ------- If reset --------- */
        if (reset) begin
            state <= T0;
            {PC_out, PC_inc, MAR_in, MEM_rd, IR_in, IR_out, A_in, B_in, ALU_out} = 0;
            {PC_in, MEM_wr} = 0;
            ALU_op = 0;
        end 
        else begin
            case (state)
                /* ----- FETCH cycle ----- */
                T0: begin
                    PC_out = 1;
                    MAR_in = 1;
                    state <= T1;
                end 
                T1: begin
                    PC_inc = 1;
                    MEM_rd = 1;
                    IR_in  = 1;
                    state <= T2;
                end

                T2: begin 
                    case (opcode)
                        OP_LDA:   state <= LDA_st1;
                        OP_ADDA:  state <= ADDA_st1;
                        OP_SUBA:  state <= SUBA_st1;
                        OP_ADDAI: state <= ADDAI_st1;
                        OP_SUBAI: state <= SUBAI_st1;
                        OP_STRA:  state <= STRA_st;
                        OP_MOVAB: state <= MOVAB_st;
                        OP_LDB:   state <= LDB_st1;
                        OP_ADDB:  state <= ADDB_st1;
                        OP_SUBB:  state <= SUBB_st1;
                        OP_ADDBI: state <= ADDBI_st1;
                        OP_SUBBI: state <= SUBBI_st1;
                        OP_STRB:  state <= STRB_st;
                        OP_MOVBA: state <= MOVBA_st;
                        default : state <= T0;
                    endcase
                end

                /* ------- LDA: A <- MEM[addr] ----------- */
                LDA_st1: begin
                    IR_out = 1;       // IR[3:0] (address) -> MAR
                    MAR_in = 1;
                    state <= LDA_st2;
                end 
                
                LDA_st2: begin 
                    MEM_rd = 1;       // read memory -> A
                    A_in   = 1;
                    state <= T0;
                end 

                /* ------- ADDA: A <- A + MEM[addr] ------ */
                ADDA_st1: begin 
                    IR_out = 1;       // address -> MAR
                    MAR_in = 1;
                    state <= ADDA_st2;
                end 

                ADDA_st2: begin 
                    MEM_rd = 1;       // mem value -> B
                    B_in   = 1;
                    state <= ADDA_st3;
                end

                ADDA_st3: begin 
                    ALU_op  = A_add_B; // A + B -> A
                    ALU_out = 1;
                    A_in    = 1;
                    state <= T0;
                end 

                /* ------- SUBA: A <- A - MEM[addr] ------ */
                SUBA_st1: begin
                    IR_out = 1;
                    MAR_in = 1;
                    state <= SUBA_st2;
                end 

                SUBA_st2: begin 
                    MEM_rd = 1;
                    B_in   = 1;
                    state <= SUBA_st3;
                end

                SUBA_st3: begin 
                    ALU_op  = A_sub_B;
                    ALU_out = 1;
                    A_in    = 1;
                    state <= T0;
                end     

                /* ------- ADDAI: A <- A + imm ------------ */
                ADDAI_st1: begin 
                    IR_out = 1;       // immediate -> B
                    B_in   = 1;
                    state <= ADDAI_st2;
                end 

                ADDAI_st2: begin 
                    ALU_op  = A_add_B;
                    ALU_out = 1;
                    A_in    = 1;
                    state <= T0;
                end 

                /* ------- SUBAI: A <- A - imm ------------ */
                SUBAI_st1: begin 
                    IR_out = 1;
                    B_in   = 1;
                    state <= SUBAI_st2;
                end 

                SUBAI_st2: begin 
                    ALU_op  = A_sub_B;
                    ALU_out = 1;
                    A_in    = 1;
                    state <= T0;
                end 

                /* ------- STRA: MEM[IR[3:0]] <- A ------- */
                STRA_st: begin 
                    IR_out = 1;       // address -> MAR
                    MAR_in = 1;
                    ALU_op = Pass_A;  // A -> bus
                    ALU_out = 1;
                    MEM_wr = 1;
                    state <= T0;
                end

                /* ------- MOVAB: B <- A ----------------- */
                MOVAB_st: begin 
                    ALU_op  = Pass_A;
                    ALU_out = 1;
                    B_in    = 1;
                    state <= T0;
                end 

                /* ------- LDB: B <- MEM[addr] ----------- */
                LDB_st1: begin
                    IR_out = 1;
                    MAR_in = 1;
                    state <= LDB_st2;
                end 
                
                LDB_st2: begin 
                    MEM_rd = 1;
                    B_in   = 1;
                    state <= T0;
                end 
                
                /* ------- ADDB: B <- B + MEM[addr] ------ */
                ADDB_st1: begin 
                    IR_out = 1;
                    MAR_in = 1;
                    state <= ADDB_st2;
                end 

                ADDB_st2: begin 
                    MEM_rd = 1;
                    A_in   = 1;         // mem value -> A
                    state <= ADDB_st3;
                end 

                ADDB_st3: begin 
                    ALU_op  = A_add_B; // A (mem) + B -> B
                    ALU_out = 1;
                    B_in    = 1;
                    state <= T0;
                end 

                /* ------- SUBB: B <- B - MEM[addr] ------ */
                SUBB_st1: begin
                    IR_out = 1;
                    MAR_in = 1;
                    state <= SUBB_st2;
                end 

                SUBB_st2: begin 
                    MEM_rd = 1;
                    A_in   = 1;         // mem value -> A
                    state <= SUBB_st3;
                end 

                SUBB_st3: begin 
                    ALU_op  = B_sub_A; // B - A -> B
                    ALU_out = 1;
                    B_in    = 1;
                    state <= T0;
                end     

                /* ------- ADDBI: B <- B + imm ----------- */
                ADDBI_st1: begin 
                    IR_out = 1;       // immediate -> A
                    A_in   = 1;
                    state <= ADDBI_st2;
                end 

                ADDBI_st2: begin 
                    ALU_op  = A_add_B; // A (imm) + B -> B
                    ALU_out = 1;
                    B_in    = 1;
                    state <= T0;
                end 

                /* ------- SUBBI: B <- B - imm ----------- */
                SUBBI_st1: begin 
                    IR_out = 1;
                    A_in   = 1;
                    state <= SUBBI_st2;
                end 

                SUBBI_st2: begin 
                    ALU_op  = B_sub_A; // B - A (imm) -> B
                    ALU_out = 1;
                    B_in    = 1;
                    state <= T0;
                end 

                /* ------- STRB: MEM[IR[3:0]] <- B ------- */
                STRB_st: begin 
                    IR_out = 1;
                    MAR_in = 1;
                    ALU_op = Pass_B;  // B -> bus
                    ALU_out = 1;
                    MEM_wr = 1;
                    state <= T0;
                end

                /* ------- MOVBA: A <- B ----------------- */
                MOVBA_st: begin 
                    ALU_op  = Pass_B;
                    ALU_out = 1;
                    A_in    = 1;
                    state <= T0;
                end 

                default: state <= T0;
            endcase
        end
    end
endmodule

src/module/register.v
module reg_A (
    input  wire       clk,
    input  wire       reset,
    input  wire       A_in,       // load enable  (from Control Unit)
    input  wire [7:0] bus,        // 8-bit shared bus
    output reg  [7:0] A_data      // current value of A (always visible)
);
    always @(posedge clk or posedge reset) begin
        if (reset)
            A_data <= 8'b0;
        else if (A_in)
            A_data <= bus;        // capture whatever is on the bus
    end
endmodule
 
 
module reg_B (
    input  wire       clk,
    input  wire       reset,
    input  wire       B_in,       // load enable  (from Control Unit)
    input  wire [7:0] bus,        // 8-bit shared bus
    output reg  [7:0] B_data      // current value of B (always visible)
);
    always @(posedge clk or posedge reset) begin
        if (reset)
            B_data <= 8'b0;
        else if (B_in)
            B_data <= bus;        // capture whatever is on the bus
    end
endmodule

src/module/alu.v
module alu(input [7:0] a, b, input [2:0] op, output reg [7:0] res);
    always @(*) begin
        case (op)
            3'b000: res = a + b;
            3'b001: res = a - b;
            3'b010: res = b - a;
            3'b011: res = a;
            3'b100: res = b;
            3'b101: res = a * b;
            3'b110: res = (b == 8'b0) ? 8'b0 : (a / b);
            3'b111: res = (a == 8'b0) ? 8'b0 : (b / a);
        endcase
    end
endmodule

src/module/memory.v
module memory(
    input [3:0] address,   
    input clk,                  
    input MEM_wr,          
    input [7:0] data_in,      
    output [7:0] data_out      
);
  reg [7:0] ram [15:0]; 

    initial begin
        integer i;
      for (i = 0; i < 16; i = i + 1) ram[i] = 8'h00; 
        ram[3] = 8'd4; 
        ram[6] = 8'd5; 
    end

  always @(posedge clk) begin
        if (MEM_wr)
            ram[address] <= data_in;
    end

    assign data_out = ram[address];

endmodule

src/module/bus.v
module bus_system(
    input PC_out,
    input MEM_rd,
    input IR_out,
    input ALU_out,
  
    input [7:0] pc_data,
    input [7:0] mem_data,
    input [7:0] ir_data,
    input [7:0] alu_data,
    
    output reg [7:0] bus_data
);

    always @(*) begin
        if (PC_out)            bus_data = pc_data;
        else if (MEM_rd)   bus_data = mem_data;
        else if (IR_out)   bus_data = ir_data;
        else if (ALU_out)  bus_data = alu_data;
        else               bus_data = 8'bz; 
    end

endmodule

src/module/cpu.v
// =============================================================
//  cpu.v  –  Top-level module (SAP-1)
//
//  Instantiates and wires:
//    control_unit, alu, bus_system, memory, reg_A, reg_B
//
//  Internal registers handled here:
//    • PC  (program counter) – driven by control_unit internally,
//          but its *output value* is exposed to the bus via PC_out
//    • MAR (memory address register)
//    • IR  (instruction register)
// =============================================================
 
module cpu (
    input  wire       clk,
    input  wire       reset,
    // Optional debug outputs so you can probe in simulation
    output wire [7:0] bus,
    output wire [7:0] A_data,
    output wire [7:0] B_data,
    output wire [7:0] IR_reg,
    output wire [3:0] state_out
);
 
    // -------------------------------------------------------
    //  Control signals (from Control Unit)
    // -------------------------------------------------------
    wire PC_out, PC_in, PC_inc;
    wire MAR_in;
    wire MEM_rd, MEM_wr;
    wire IR_in,  IR_out;
    wire A_in,   B_in;
    wire ALU_out;
    wire [2:0] ALU_op;
 
    // -------------------------------------------------------
    //  Internal registers: MAR and IR
    // -------------------------------------------------------
    reg [3:0] MAR;   // only needs 4 bits (16-byte address space)
    reg [7:0] IR;    // full 8-bit instruction word
 
    // MAR: latch lower 4 bits of bus when MAR_in is asserted
    always @(posedge clk or posedge reset) begin
        if (reset)
            MAR <= 4'b0;
        else if (MAR_in)
            MAR <= bus[3:0];
    end
 
    // IR: latch full bus when IR_in is asserted
    always @(posedge clk or posedge reset) begin
        if (reset)
            IR <= 8'b0;
        else if (IR_in)
            IR <= bus;
    end
 
    assign IR_reg = IR;   // expose for debug
 
    // -------------------------------------------------------
    //  PC output to bus
    //    control_unit manages the PC counter internally.
    //    It exposes a PC_out control signal; we need the
    //    actual PC *value*.  Because the PC lives inside
    //    control_unit, we re-use the MAR value after T0
    //    (where MAR already captured PC).  Alternatively,
    //    expose PC from control_unit.  Here we expose it
    //    as a wire driven by a small helper register below.
    // -------------------------------------------------------
    reg  [7:0] PC_val;   // shadow of the PC inside control_unit
 
    // We reconstruct PC_val by watching PC_inc (same logic as in CU)
    always @(posedge clk or posedge reset) begin
        if (reset)
            PC_val <= 8'b0;
        else if (PC_inc)
            PC_val <= PC_val + 4;   // matches control_unit increment
    end
 
    // -------------------------------------------------------
    //  Data wires between modules
    // -------------------------------------------------------
    wire [7:0] mem_data_out;
    wire [7:0] alu_result;
    wire [7:0] A_wire, B_wire;
 
    // IR lower 4 bits zero-extended → bus when IR_out is asserted
    // (used as address or immediate value)
    wire [7:0] ir_bus_data = {4'b0000, IR[3:0]};
 
    // -------------------------------------------------------
    //  Bus
    // -------------------------------------------------------
    bus_system BUS (
        .PC_out   (PC_out),
        .MEM_rd   (MEM_rd),
        .IR_out   (IR_out),
        .ALU_out  (ALU_out),
        .pc_data  (PC_val),
        .mem_data (mem_data_out),
        .ir_data  (ir_bus_data),
        .alu_data (alu_result),
        .bus_data (bus)
    );
 
    // -------------------------------------------------------
    //  Memory
    // -------------------------------------------------------
    memory MEM (
        .address  (MAR),
        .clk      (clk),
        .MEM_wr   (MEM_wr),
        .data_in  (bus),
        .data_out (mem_data_out)
    );
 
    // -------------------------------------------------------
    //  ALU
    //    The ALU opcode mapping used by control_unit:
    //      A_add_B = 3'b000  → alu op 000 (a+b)   ✓
    //      A_sub_B = 3'b001  → alu op 001 (a-b)   ✓
    //      B_sub_A = 3'b010  → alu op 001 (a-b)   * see note
    //      Pass_A  = 3'b011  → alu op 110 (pass a)* remapped below
    //      Pass_B  = 3'b100  → alu op 110 (pass b)* remapped below
    //      A_mul_B = 3'b101  → custom (not in alu) * extend if needed
    //      A_div_B = 3'b110  → custom              * extend if needed
    //      B_div_A = 3'b111  → custom              * extend if needed
    //
    //  NOTE: alu.v uses a different encoding than control_unit.
    //  We add a small mapping layer here so both files stay untouched.
    // -------------------------------------------------------
    reg [2:0] alu_op_mapped;
 
    always @(*) begin
        case (ALU_op)
            3'b000: alu_op_mapped = 3'b000; // A + B
            3'b001: alu_op_mapped = 3'b001; // A - B
            3'b010: alu_op_mapped = 3'b001; // B - A  → feed swapped (see swap below)
            3'b011: alu_op_mapped = 3'b110; // Pass A
            3'b100: alu_op_mapped = 3'b110; // Pass B → feed B as 'a' (see swap)
            // Mul/Div – extend alu.v to support these; placeholder → 0
            default: alu_op_mapped = 3'b000;
        endcase
    end
 
    // For B_sub_A (op=010) swap inputs so alu computes B-A correctly
    // For Pass_B  (op=100) put B on the 'a' input so Pass_A logic works
    wire [7:0] alu_in_a = (ALU_op == 3'b010 || ALU_op == 3'b100) ? B_wire : A_wire;
    wire [7:0] alu_in_b = (ALU_op == 3'b010 || ALU_op == 3'b100) ? A_wire : B_wire;
 
    alu ALU (
        .a   (alu_in_a),
        .b   (alu_in_b),
        .op  (alu_op_mapped),
        .res (alu_result)
    );
 
    // -------------------------------------------------------
    //  Registers A and B
    // -------------------------------------------------------
    reg_A REGA (
        .clk    (clk),
        .reset  (reset),
        .A_in   (A_in),
        .bus    (bus),
        .A_data (A_wire)
    );
 
    reg_B REGB (
        .clk    (clk),
        .reset  (reset),
        .B_in   (B_in),
        .bus    (bus),
        .B_data (B_wire)
    );
 
    assign A_data = A_wire;
    assign B_data = B_wire;
 
    // -------------------------------------------------------
    //  Control Unit
    // -------------------------------------------------------
    control_unit CU (
        .clk     (clk),
        .reset   (reset),
        .opcode  (IR[7:4]),    // upper nibble of IR
        .PC_out  (PC_out),
        .PC_in   (PC_in),
        .PC_inc  (PC_inc),
        .MAR_in  (MAR_in),
        .MEM_rd  (MEM_rd),
        .MEM_wr  (MEM_wr),
        .IR_in   (IR_in),
        .IR_out  (IR_out),
        .A_in    (A_in),
        .B_in    (B_in),
        .ALU_out (ALU_out),
        .ALU_op  (ALU_op),
        .state   (state_out)
    );
 
endmodule

test/tb_cpu.v
// =============================================================
//  tb_cpu.v  –  Testbench for SAP-1 top-level cpu module
//
//  Tests:
//    1. LDA 3   → A should become 4  (ram[3]=4)
//    2. ADD 6   → A should become 9  (ram[6]=5, 4+5=9)
// =============================================================

`timescale 1ns/1ps

module tb_cpu;

    reg  clk, reset;
    wire [7:0] bus;
    wire [7:0] A_data, B_data, IR_reg;
    wire [3:0] state_out;

    // Instantiate DUT
    cpu DUT (
        .clk      (clk),
        .reset    (reset),
        .bus      (bus),
        .A_data   (A_data),
        .B_data   (B_data),
        .IR_reg   (IR_reg),
        .state_out(state_out)
    );

    // Clock: 10 ns period
    initial clk = 0;
    always #5 clk = ~clk;

    // ---- Load test program into memory ----
    // Instruction encoding:
    //   LDA  addr  = opcode 0000 | addr[3:0]  → 8'h03  (LDA  address 3)
    //   ADDA addr  = opcode 0001 | addr[3:0]  → 8'h16  (ADDA address 6)
    initial begin
        // Pre-load instructions directly into memory module
        // ram[0] = LDA 3  = 0000_0011 = 8'h03
        // ram[4] = ADD 6  = 0001_0110 = 8'h16
        // (PC increments by 4 each fetch)
        DUT.MEM.ram[0] = 8'h03;   // LDA  3
        DUT.MEM.ram[4] = 8'h16;   // ADDA 6
        // Data (already set in memory.v initial block, but set again for safety)
        DUT.MEM.ram[3] = 8'd4;
        DUT.MEM.ram[6] = 8'd5;
    end

    // ---- Stimulus ----
    initial begin
        $dumpfile("tb_cpu.vcd");
        $dumpvars(0, tb_cpu);

        // Reset for 2 cycles
        reset = 1;
        @(posedge clk); #1;
        @(posedge clk); #1;
        reset = 0;

        // Run for enough cycles to complete both instructions
        // Each instruction takes ~3-4 clock cycles; give 40 cycles total
        repeat (40) @(posedge clk);

        // ---- Check results ----
        $display("=== SAP-1 Simulation Results ===");
        $display("A register = %0d (expected 9)", A_data);
        $display("B register = %0d", B_data);
        if (A_data === 8'd9)
            $display("PASS: LDA 3 + ADD 6 => A = 9");
        else
            $display("FAIL: A = %0d (expected 9)", A_data);

        $finish;
    end

    // ---- Monitor every clock edge ----
    initial begin
        $monitor("t=%0t | state=%0d | bus=%02h | A=%0d | B=%0d | IR=%02h",
                  $time, state_out, bus, A_data, B_data, IR_reg);
    end

endmodule

tb_cpu.vcd
$date
	Sat May 16 12:19:33 2026
$end
$version
	Icarus Verilog
$end
$timescale
	1ps
$end
$scope module tb_cpu $end
$var wire 4 ! state_out [3:0] $end
$var wire 8 " bus [7:0] $end
$var wire 8 # IR_reg [7:0] $end
$var wire 8 $ B_data [7:0] $end
$var wire 8 % A_data [7:0] $end
$var reg 1 & clk $end
$var reg 1 ' reset $end
$scope module DUT $end
$var wire 8 ( A_data [7:0] $end
$var wire 8 ) B_data [7:0] $end
$var wire 8 * IR_reg [7:0] $end
$var wire 1 & clk $end
$var wire 1 ' reset $end
$var wire 4 + state_out [3:0] $end
$var wire 8 , mem_data_out [7:0] $end
$var wire 8 - ir_bus_data [7:0] $end
$var wire 8 . bus [7:0] $end
$var wire 8 / alu_result [7:0] $end
$var wire 8 0 alu_in_b [7:0] $end
$var wire 8 1 alu_in_a [7:0] $end
$var wire 1 2 PC_out $end
$var wire 1 3 PC_inc $end
$var wire 1 4 PC_in $end
$var wire 1 5 MEM_wr $end
$var wire 1 6 MEM_rd $end
$var wire 1 7 MAR_in $end
$var wire 1 8 IR_out $end
$var wire 1 9 IR_in $end
$var wire 8 : B_wire [7:0] $end
$var wire 1 ; B_in $end
$var wire 8 < A_wire [7:0] $end
$var wire 1 = A_in $end
$var wire 1 > ALU_out $end
$var wire 3 ? ALU_op [2:0] $end
$var reg 8 @ IR [7:0] $end
$var reg 4 A MAR [3:0] $end
$var reg 8 B PC_val [7:0] $end
$var reg 3 C alu_op_mapped [2:0] $end
$scope module ALU $end
$var wire 8 D a [7:0] $end
$var wire 8 E b [7:0] $end
$var wire 3 F op [2:0] $end
$var reg 8 G res [7:0] $end
$upscope $end
$scope module BUS $end
$var wire 8 H alu_data [7:0] $end
$var wire 8 I ir_data [7:0] $end
$var wire 8 J pc_data [7:0] $end
$var wire 8 K mem_data [7:0] $end
$var wire 1 2 PC_out $end
$var wire 1 6 MEM_rd $end
$var wire 1 8 IR_out $end
$var wire 1 > ALU_out $end
$var reg 8 L bus_data [7:0] $end
$upscope $end
$scope module CU $end
$var wire 1 & clk $end
$var wire 4 M opcode [3:0] $end
$var wire 1 ' reset $end
$var parameter 32 N ADDAI_st1 $end
$var parameter 32 O ADDAI_st2 $end
$var parameter 32 P ADDA_st1 $end
$var parameter 32 Q ADDA_st2 $end
$var parameter 32 R ADDA_st3 $end
$var parameter 32 S ADDBI_st1 $end
$var parameter 32 T ADDBI_st2 $end
$var parameter 32 U ADDB_st1 $end
$var parameter 32 V ADDB_st2 $end
$var parameter 32 W ADDB_st3 $end
$var parameter 3 X A_add_B $end
$var parameter 3 Y A_div_B $end
$var parameter 3 Z A_mul_B $end
$var parameter 3 [ A_sub_B $end
$var parameter 3 \ B_div_A $end
$var parameter 3 ] B_sub_A $end
$var parameter 32 ^ LDA_st1 $end
$var parameter 32 _ LDA_st2 $end
$var parameter 32 ` LDB_st1 $end
$var parameter 32 a LDB_st2 $end
$var parameter 32 b MOVAB_st $end
$var parameter 32 c MOVBA_st $end
$var parameter 4 d OP_ADDA $end
$var parameter 4 e OP_ADDAI $end
$var parameter 4 f OP_ADDB $end
$var parameter 4 g OP_ADDBI $end
$var parameter 4 h OP_LDA $end
$var parameter 4 i OP_LDB $end
$var parameter 4 j OP_MOVAB $end
$var parameter 4 k OP_MOVBA $end
$var parameter 4 l OP_STRA $end
$var parameter 4 m OP_STRB $end
$var parameter 4 n OP_SUBA $end
$var parameter 4 o OP_SUBAI $end
$var parameter 4 p OP_SUBB $end
$var parameter 4 q OP_SUBBI $end
$var parameter 3 r Pass_A $end
$var parameter 3 s Pass_B $end
$var parameter 32 t STRA_st $end
$var parameter 32 u STRB_st $end
$var parameter 32 v SUBAI_st1 $end
$var parameter 32 w SUBAI_st2 $end
$var parameter 32 x SUBA_st1 $end
$var parameter 32 y SUBA_st2 $end
$var parameter 32 z SUBA_st3 $end
$var parameter 32 { SUBBI_st1 $end
$var parameter 32 | SUBBI_st2 $end
$var parameter 32 } SUBB_st1 $end
$var parameter 32 ~ SUBB_st2 $end
$var parameter 32 !" SUBB_st3 $end
$var parameter 32 "" T0 $end
$var parameter 32 #" T1 $end
$var parameter 32 $" T2 $end
$var reg 3 %" ALU_op [2:0] $end
$var reg 1 > ALU_out $end
$var reg 1 = A_in $end
$var reg 1 ; B_in $end
$var reg 1 9 IR_in $end
$var reg 1 8 IR_out $end
$var reg 1 7 MAR_in $end
$var reg 1 6 MEM_rd $end
$var reg 1 5 MEM_wr $end
$var reg 1 4 PC_in $end
$var reg 1 3 PC_inc $end
$var reg 1 2 PC_out $end
$var reg 4 &" state [3:0] $end
$upscope $end
$scope module MEM $end
$var wire 1 5 MEM_wr $end
$var wire 4 '" address [3:0] $end
$var wire 1 & clk $end
$var wire 8 (" data_in [7:0] $end
$var wire 8 )" data_out [7:0] $end
$scope begin $unm_blk_44 $end
$var integer 32 *" i [31:0] $end
$upscope $end
$upscope $end
$scope module REGA $end
$var wire 1 = A_in $end
$var wire 8 +" bus [7:0] $end
$var wire 1 & clk $end
$var wire 1 ' reset $end
$var reg 8 ," A_data [7:0] $end
$upscope $end
$scope module REGB $end
$var wire 1 ; B_in $end
$var wire 8 -" bus [7:0] $end
$var wire 1 & clk $end
$var wire 1 ' reset $end
$var reg 8 ." B_data [7:0] $end
$upscope $end
$upscope $end
$upscope $end
$enddefinitions $end
$comment Show the parameter values. $end
$dumpall
b10 $"
b1 #"
b0 ""
b11001 !"
b11000 ~
b10111 }
b11101 |
b11100 {
b1011 z
b1010 y
b1001 x
b1111 w
b1110 v
b11110 u
b10000 t
b100 s
b11 r
b1100 q
b1010 p
b100 o
b10 n
b1101 m
b101 l
b1110 k
b110 j
b1000 i
b0 h
b1011 g
b1001 f
b11 e
b1 d
b11111 c
b10001 b
b10011 a
b10010 `
b101 _
b100 ^
b10 ]
b111 \
b1 [
b101 Z
b110 Y
b0 X
b10110 W
b10101 V
b10100 U
b11011 T
b11010 S
b1000 R
b111 Q
b110 P
b1101 O
b1100 N
$end
#0
$dumpvars
b0 ."
bz -"
b0 ,"
bz +"
b10000 *"
b11 )"
bz ("
b0 '"
b0 &"
b0 %"
b0 M
bz L
b11 K
b0 J
b0 I
b0 H
b0 G
b0 F
b0 E
b0 D
b0 C
b0 B
b0 A
b0 @
b0 ?
0>
0=
b0 <
0;
b0 :
09
08
07
06
05
04
03
02
b0 1
b0 0
b0 /
bz .
b0 -
b11 ,
b0 +
b0 *
b0 )
b0 (
1'
0&
b0 %
b0 $
b0 #
bz "
b0 !
$end
#5000
1&
#10000
0&
#15000
1&
#16000
0'
#20000
0&
#25000
bx ,
bx K
bx )"
bz A
bz '"
b1 !
b1 +
b1 &"
b0 "
b0 .
b0 L
b0 ("
b0 +"
b0 -"
17
12
1&
#30000
0&
#35000
b11 ,
b11 K
b11 )"
b10 !
b10 +
b10 &"
b0 A
b0 '"
b11 "
b11 .
b11 L
b11 ("
b11 +"
b11 -"
19
16
13
02
07
1&
#40000
0&
#45000
b100 !
b100 +
b100 &"
bz "
bz .
bz L
bz ("
bz +"
bz -"
03
06
09
1&
#50000
0&
#55000
b101 !
b101 +
b101 &"
b0 "
b0 .
b0 L
b0 ("
b0 +"
b0 -"
17
18
1&
#60000
0&
#65000
b0 !
b0 +
b0 &"
b11 "
b11 .
b11 L
b11 ("
b11 +"
b11 -"
1=
16
07
08
1&
#70000
0&
#75000
b1 !
b1 +
b1 &"
b0 "
b0 .
b0 L
b0 ("
b0 +"
b0 -"
17
12
06
0=
1&
#80000
0&
#85000
b100 B
b100 J
b10 !
b10 +
b10 &"
b11 "
b11 .
b11 L
b11 ("
b11 +"
b11 -"
19
16
13
02
07
1&
#90000
0&
#95000
b11 -
b11 I
b100 !
b100 +
b100 &"
b11 #
b11 *
b11 @
b1000 B
b1000 J
bz "
bz .
bz L
bz ("
bz +"
bz -"
03
06
09
1&
#100000
0&
#105000
bx ,
bx K
bx )"
bz A
bz '"
b101 !
b101 +
b101 &"
b11 "
b11 .
b11 L
b11 ("
b11 +"
b11 -"
17
18
1&
#110000
0&
#115000
b11 /
b11 G
b11 H
b11 1
b11 D
b100 ,
b100 K
b100 )"
b11 %
b11 (
b11 <
b11 ,"
b0 !
b0 +
b0 &"
b11 A
b11 '"
b100 "
b100 .
b100 L
b100 ("
b100 +"
b100 -"
1=
16
07
08
1&
#120000
0&
#125000
b100 /
b100 G
b100 H
b10110 ,
b10110 K
b10110 )"
b100 1
b100 D
b100 A
b100 '"
b1 !
b1 +
b1 &"
b100 %
b100 (
b100 <
b100 ,"
b1000 "
b1000 .
b1000 L
b1000 ("
b1000 +"
b1000 -"
17
12
06
0=
1&
#130000
0&
#135000
b0 ,
b0 K
b0 )"
b10 !
b10 +
b10 &"
b1000 A
b1000 '"
b0 "
b0 .
b0 L
b0 ("
b0 +"
b0 -"
19
16
13
02
07
1&
#140000
0&
#145000
b100 !
b100 +
b100 &"
bz "
bz .
bz L
bz ("
bz +"
bz -"
03
06
09
1&
#150000
0&
#155000
b101 !
b101 +
b101 &"
b11 "
b11 .
b11 L
b11 ("
b11 +"
b11 -"
17
18
1&
#160000
0&
#165000
b0 !
b0 +
b0 &"
b0 "
b0 .
b0 L
b0 ("
b0 +"
b0 -"
1=
16
07
08
1&
#170000
0&
#175000
b1 !
b1 +
b1 &"
b1000 "
b1000 .
b1000 L
b1000 ("
b1000 +"
b1000 -"
17
12
06
0=
1&
#180000
0&
#185000
b1000 -
b1000 I
b1100 B
b1100 J
b1000 #
b1000 *
b1000 @
b10 !
b10 +
b10 &"
b0 "
b0 .
b0 L
b0 ("
b0 +"
b0 -"
19
16
13
02
07
1&
#190000
0&
#195000
b0 -
b0 I
b100 !
b100 +
b100 &"
b0 #
b0 *
b0 @
b10000 B
b10000 J
bz "
bz .
bz L
bz ("
bz +"
bz -"
03
06
09
1&
#200000
0&
#205000
bx ,
bx K
bx )"
bz A
bz '"
b101 !
b101 +
b101 &"
b0 "
b0 .
b0 L
b0 ("
b0 +"
b0 -"
17
18
1&
#210000
0&
#215000
b0 /
b0 G
b0 H
b0 1
b0 D
b11 ,
b11 K
b11 )"
b0 %
b0 (
b0 <
b0 ,"
b0 !
b0 +
b0 &"
b0 A
b0 '"
b11 "
b11 .
b11 L
b11 ("
b11 +"
b11 -"
1=
16
07
08
1&
#220000
0&
#225000
b11 /
b11 G
b11 H
b100 ,
b100 K
b100 )"
b11 1
b11 D
b11 A
b11 '"
b1 !
b1 +
b1 &"
b11 %
b11 (
b11 <
b11 ,"
b10000 "
b10000 .
b10000 L
b10000 ("
b10000 +"
b10000 -"
17
12
06
0=
1&
#230000
0&
#235000
b11 ,
b11 K
b11 )"
b10 !
b10 +
b10 &"
b0 A
b0 '"
b11 "
b11 .
b11 L
b11 ("
b11 +"
b11 -"
19
16
13
02
07
1&
#240000
0&
#245000
b100 !
b100 +
b100 &"
bz "
bz .
bz L
bz ("
bz +"
bz -"
03
06
09
1&
#250000
0&
#255000
b101 !
b101 +
b101 &"
b0 "
b0 .
b0 L
b0 ("
b0 +"
b0 -"
17
18
1&
#260000
0&
